iso3166KOR/__init__.py
iso3166KOR/py.typed
iso3166KOR-0.0.1.dist-info/LICENSE.txt
iso3166KOR-0.0.1.dist-info/METADATA
iso3166KOR-0.0.1.dist-info/WHEEL
iso3166KOR-0.0.1.dist-info/top_level.txt
iso3166KOR-0.0.1.dist-info/RECORD
