Metadata-Version: 2.1
Name: iso3166KOR
Version: 0.0.1
Summary: Self-contained ISO 3166-1 country definitions.
Home-page: https://github.com/JaeHyunL/iso3166KOR
Author: JaeHyunL
Author-email: swaa23@gmail.com
License: MIT
Keywords: iso 3166-1:KOR,iso country Korean
Platform: UNKNOWN
Classifier: Development Status :: 5 - Production/Stable
Classifier: License :: OSI Approved :: MIT License
Classifier: Intended Audience :: Developers
Classifier: Natural Language :: English
Classifier: Programming Language :: Python
Classifier: Programming Language :: Python :: 3
Classifier: Programming Language :: Python :: 3 :: Only
Classifier: Programming Language :: Python :: 3.6
Classifier: Programming Language :: Python :: 3.7
Classifier: Programming Language :: Python :: 3.8
Classifier: Programming Language :: Python :: 3.9
Classifier: Programming Language :: Python :: 3.10
Classifier: Programming Language :: Python :: 3.11
Requires-Python: >=3.6
License-File: LICENSE.txt
